hierarchical/__init__.py
hierarchical/enums.py
hierarchical/hierarchy_builder.py
hierarchical/hierarchy_builder_metadata.py
hierarchical/parsers.py
hierarchical/postprocessor.py
hierarchical/types/__init__.py
hierarchical/types/hierarchical_header.py
docling_hierarchical_pdf-0.1.3.dist-info/METADATA
docling_hierarchical_pdf-0.1.3.dist-info/WHEEL
docling_hierarchical_pdf-0.1.3.dist-info/licenses/LICENSE
docling_hierarchical_pdf-0.1.3.dist-info/RECORD
