Metadata-Version: 2.4
Name: docling-hierarchical-pdf
Version: 0.1.3
Summary: This package enables inference of header hierarchy in the docling PDF parsing pipeline.
Project-URL: Homepage, https://krrome.github.io/docling-hierarchical-pdf/
Project-URL: Repository, https://github.com/krrome/docling-hierarchical-pdf
Project-URL: Documentation, https://krrome.github.io/docling-hierarchical-pdf/
Author-email: Roman Kayan <rkreuzh@gmail.com>
License-File: LICENSE
Keywords: python
Classifier: Intended Audience :: Developers
Classifier: Programming Language :: Python
Classifier: Programming Language :: Python :: 3
Classifier: Programming Language :: Python :: 3.9
Classifier: Programming Language :: Python :: 3.10
Classifier: Programming Language :: Python :: 3.11
Classifier: Programming Language :: Python :: 3.12
Classifier: Programming Language :: Python :: 3.13
Classifier: Topic :: Software Development :: Libraries :: Python Modules
Requires-Python: <4.0,>=3.9
Requires-Dist: docling>=2.53.0
Requires-Dist: numpy>=1.19.5
Requires-Dist: pymupdf>=1.26.4
Requires-Dist: scikit-learn>=1.6.0
